pulse_workflow_mcp/__init__.py
pulse_workflow_mcp/__main__.py
pulse_workflow_mcp/cli.py
pulse_workflow_mcp/config.py
pulse_workflow_mcp/dify_client.py
pulse_workflow_mcp/py.typed
pulse_workflow_mcp/server.py
pulse_workflow_mcp/prompts/__init__.py
pulse_workflow_mcp/prompts/workflow_context.py
pulse_workflow_mcp/resources/__init__.py
pulse_workflow_mcp/resources/node_types.py
pulse_workflow_mcp/resources/workflow_resource.py
pulse_workflow_mcp/skills/pulse/SKILL.md
pulse_workflow_mcp/skills/pulse/references/discovery-flow.md
pulse_workflow_mcp/skills/pulse/references/examples.md
pulse_workflow_mcp/skills/pulse/references/mcp-tools.md
pulse_workflow_mcp/skills/pulse/references/node-types.md
pulse_workflow_mcp/skills/pulse-create/SKILL.md
pulse_workflow_mcp/skills/pulse-edit/SKILL.md
pulse_workflow_mcp/skills/pulse-publish/SKILL.md
pulse_workflow_mcp-0.1.4.dist-info/METADATA
pulse_workflow_mcp-0.1.4.dist-info/WHEEL
pulse_workflow_mcp-0.1.4.dist-info/entry_points.txt
pulse_workflow_mcp-0.1.4.dist-info/licenses/LICENSE
pulse_workflow_mcp-0.1.4.dist-info/RECORD
