Metadata-Version: 2.4
Name: pulse-workflow-mcp
Version: 0.1.4
Summary: MCP server for interacting with Pulse workflows from Claude Code
Project-URL: Homepage, https://github.com/Pulse-Intelligence/pulse-workflow-mcp
Project-URL: Repository, https://github.com/Pulse-Intelligence/pulse-workflow-mcp
Project-URL: Issues, https://github.com/Pulse-Intelligence/pulse-workflow-mcp/issues
Project-URL: Changelog, https://github.com/Pulse-Intelligence/pulse-workflow-mcp/blob/main/CHANGELOG.md
Author: Pulse Intelligence
License: MIT
License-File: LICENSE
Keywords: ai,automation,claude,llm,mcp,pulse,workflow
Classifier: Development Status :: 3 - Alpha
Classifier: Intended Audience :: Developers
Classifier: License :: OSI Approved :: MIT License
Classifier: Programming Language :: Python :: 3
Classifier: Programming Language :: Python :: 3.11
Classifier: Programming Language :: Python :: 3.12
Requires-Python: >=3.11
Requires-Dist: httpx[http2]>=0.25.0
Requires-Dist: mcp>=1.0.0
Requires-Dist: pydantic-settings>=2.0.0
Requires-Dist: pydantic>=2.0.0
Requires-Dist: pylint>=4.0.4
Provides-Extra: dev
Requires-Dist: pytest-asyncio>=0.23.0; extra == 'dev'
Requires-Dist: pytest>=8.0.0; extra == 'dev'
Requires-Dist: respx>=0.21.0; extra == 'dev'
Requires-Dist: ruff>=0.4.0; extra == 'dev'
